configbutler
