Metadata-Version: 1.1
Name: configbutler
Version: 0.1.2
Summary: Service to manage generation of server config from various configuration sources
Home-page: https://github.com/stevemac007/configbutler
Author: Steve Mactaggart
Author-email: steve@whitesquaresoft.com
License: MIT
Download-URL: https://github.com/stevemac007/configbutler/archive/0.1.2.tar.gz
Keywords: config configuration generation
Platform: UNKNOWN
Classifier: Development Status :: 3 - Alpha
Classifier: Environment :: Console
Classifier: Operating System :: POSIX :: Linux
Classifier: Intended Audience :: Developers
Classifier: Intended Audience :: System Administrators
Classifier: Topic :: System :: Boot
Classifier: Topic :: Software Development :: Code Generators
Classifier: Topic :: Utilities
Classifier: License :: OSI Approved :: MIT License
Classifier: Programming Language :: Python :: 2
Classifier: Programming Language :: Python :: 2.6
Classifier: Programming Language :: Python :: 2.7
